dynatalk/__init__.py
dynatalk/agent.py
dynatalk/broker.py
dynatalk/cli_monitor.py
dynatalk/space.py
dynatalk/supervisor.py
dynatalk-0.7.3.dist-info/METADATA
dynatalk-0.7.3.dist-info/WHEEL
dynatalk-0.7.3.dist-info/entry_points.txt
dynatalk-0.7.3.dist-info/RECORD
