Metadata-Version: 2.1
Name: dynatalk
Version: 0.7.3
Summary: 
Author: wwj718
Author-email: wuwenjie718@gmail.com
Requires-Python: >=3.8,<4.0
Classifier: Programming Language :: Python :: 3
Classifier: Programming Language :: Python :: 3.8
Classifier: Programming Language :: Python :: 3.9
Classifier: Programming Language :: Python :: 3.10
Classifier: Programming Language :: Python :: 3.11
Requires-Dist: amqtt (>=0.11.0b1,<0.12.0)
Requires-Dist: paho-mqtt (>=1.6.1,<2.0.0)
